setup.py
legos/__init__.py
legos/legos.py
legos.egg-info/PKG-INFO
legos.egg-info/SOURCES.txt
legos.egg-info/dependency_links.txt
legos.egg-info/namespace_packages.txt
legos.egg-info/top_level.txt