Metadata-Version: 1.1
Name: legos
Version: 0.1.1.dev2
Summary: Collection of Legos (plugins) for the Legobot framework
Home-page: https://github.com/bbriggs/Legos
Author: Brenton Briggs II
Author-email: UNKNOWN
License: GPLv3
Platform: UNKNOWN
Classifier: License :: OSI Approved :: GNU General Public License v3 (GPLv3)
Classifier: Programming Language :: Python :: 3
